dead_simple_singleton/__init__.py
dead_simple_singleton/src/singleton.py
dead_simple_singleton-1.0.0.dist-info/METADATA
dead_simple_singleton-1.0.0.dist-info/WHEEL
dead_simple_singleton-1.0.0.dist-info/RECORD
