Metadata-Version: 2.1
Name: dead-simple-singleton
Version: 1.0.0
Summary: 
Author: julianstoerig
Author-email: julian.stoerig@gmail.com
Requires-Python: >=3.12,<4.0
Classifier: Programming Language :: Python :: 3
Classifier: Programming Language :: Python :: 3.12
